rl/__init__.py
showcase/__init__.py
showcase/assembler/__init__.py
showcase/assembler/_interface.py
showcase/assembler/_types.py
showcase/assembler/simple.py
showcase/assembler/tests/__init__.py
showcase/assembler/tests/test_simple.py
showcase/database/__init__.py
showcase/database/_interface.py
showcase/database/_types.py
showcase/database/simple.py
showcase/database/tests/__init__.py
showcase/database/tests/test_simple.py
showcase/maker/__init__.py
showcase/maker/_types.py
showcase/maker/simple.py
showcase/maker/tests/__init__.py
showcase/maker/tests/test_simple.py
decoded-0.0.1.dist-info/LICENSE
decoded-0.0.1.dist-info/METADATA
decoded-0.0.1.dist-info/WHEEL
decoded-0.0.1.dist-info/top_level.txt
decoded-0.0.1.dist-info/RECORD
